katana_public_api_client/__init__.py
katana_public_api_client/client.py
katana_public_api_client/client_types.py
katana_public_api_client/errors.py
katana_public_api_client/katana_client.py
katana_public_api_client/log_setup.py
katana_public_api_client/py.typed
katana_public_api_client/utils.py
katana_public_api_client/api/__init__.py
katana_public_api_client/api/additional_costs/__init__.py
katana_public_api_client/api/additional_costs/get_additional_costs.py
katana_public_api_client/api/batch/__init__.py
katana_public_api_client/api/batch/create_batch.py
katana_public_api_client/api/batch/get_batch_stock.py
katana_public_api_client/api/batch/update_batch_stock.py
katana_public_api_client/api/bom_row/__init__.py
katana_public_api_client/api/bom_row/batch_create_bom_rows.py
katana_public_api_client/api/bom_row/create_bom_row.py
katana_public_api_client/api/bom_row/delete_bom_row.py
katana_public_api_client/api/bom_row/get_all_bom_rows.py
katana_public_api_client/api/bom_row/update_bom_row.py
katana_public_api_client/api/custom_fields/__init__.py
katana_public_api_client/api/custom_fields/get_all_custom_fields_collections.py
katana_public_api_client/api/customer/__init__.py
katana_public_api_client/api/customer/create_customer.py
katana_public_api_client/api/customer/delete_customer.py
katana_public_api_client/api/customer/get_all_customers.py
katana_public_api_client/api/customer/update_customer.py
katana_public_api_client/api/customer_address/__init__.py
katana_public_api_client/api/customer_address/create_customer_address.py
katana_public_api_client/api/customer_address/delete_customer_address.py
katana_public_api_client/api/customer_address/get_all_customer_addresses.py
katana_public_api_client/api/customer_address/update_customer_address.py
katana_public_api_client/api/factory/__init__.py
katana_public_api_client/api/factory/get_factory.py
katana_public_api_client/api/inventory/__init__.py
katana_public_api_client/api/inventory/create_inventory_reorder_point.py
katana_openapi_client-0.43.0.dist-info/METADATA
katana_openapi_client-0.43.0.dist-info/WHEEL
katana_openapi_client-0.43.0.dist-info/entry_points.txt
katana_openapi_client-0.43.0.dist-info/licenses/LICENSE
katana_openapi_client-0.43.0.dist-info/RECORD
