Metadata-Version: 2.4
Name: katana-openapi-client
Version: 0.43.0
Summary: A modern, pythonic Katana Manufacturing ERP API client with automatic retries, rate limiting, and smart pagination
Project-URL: Homepage, https://github.com/dougborg/katana-openapi-client
Project-URL: Repository, https://github.com/dougborg/katana-openapi-client
Project-URL: Documentation, https://dougborg.github.io/katana-openapi-client/
Project-URL: Bug Tracker, https://github.com/dougborg/katana-openapi-client/issues
Project-URL: Changelog, https://github.com/dougborg/katana-openapi-client/blob/main/docs/CHANGELOG.md
Author-email: Doug Borg <dougborg@dougborg.org>
Maintainer-email: Doug Borg <dougborg@dougborg.org>
License: MIT
License-File: LICENSE
Keywords: api-client,async,erp,httpx,katana,manufacturing,openapi,pagination,rate-limiting,retry
Classifier: Development Status :: 4 - Beta
Classifier: Intended Audience :: Developers
Classifier: License :: OSI Approved :: MIT License
Classifier: Operating System :: OS Independent
Classifier: Programming Language :: Python :: 3
Classifier: Programming Language :: Python :: 3.12
Classifier: Programming Language :: Python :: 3.13
Classifier: Programming Language :: Python :: 3.14
Classifier: Topic :: Internet :: WWW/HTTP :: HTTP Servers
Classifier: Topic :: Office/Business
Classifier: Topic :: Software Development :: Libraries :: Python Modules
Classifier: Typing :: Typed
Requires-Python: >=3.12
Requires-Dist: attrs>=24.0.0
Requires-Dist: email-validator>=2.2.0
Requires-Dist: httpx-retries>=0.4.5
Requires-Dist: httpx>=0.28.1
Requires-Dist: pydantic>=2.12.0
Requires-Dist: python-dateutil>=2.9.0
Requires-Dist: python-dotenv>=1.0.0
Requires-Dist: tenacity>=9.1.0
Requires-Dist: typing-extensions>=4.13.0
Requires-Dist: urllib3>=2.6.0
Provides-Extra: dev
Requires-Dist: build>=1.2.0; extra == 'dev'
Requires-Dist: datamodel-code-generator>=0.27.0; extra == 'dev'
Requires-Dist: mdformat-gfm>=0.4.1; extra == 'dev'
Requires-Dist: mdformat-tables>=1.0.0; extra == 'dev'
Requires-Dist: mdformat-toc>=0.3.0; extra == 'dev'
Requires-Dist: mdformat>=0.7.21; extra == 'dev'
Requires-Dist: openapi-python-client>=0.25.2; extra == 'dev'
Requires-Dist: openapi-spec-validator>=0.7.0; extra == 'dev'
Requires-Dist: pre-commit>=4.5.0; extra == 'dev'
Requires-Dist: pytest-asyncio>=0.26.0; extra == 'dev'
Requires-Dist: pytest-cov>=7.0.0; extra == 'dev'
Requires-Dist: pytest-mock>=3.14.0; extra == 'dev'
Requires-Dist: pytest-timeout>=2.4.0; extra == 'dev'
Requires-Dist: pytest-xdist>=3.6.1; extra == 'dev'
Requires-Dist: pytest>=9.0.0; extra == 'dev'
Requires-Dist: python-semantic-release>=10.5.0; extra == 'dev'
Requires-Dist: pyyaml>=6.0.0; extra == 'dev'
Requires-Dist: ruff>=0.14.0; extra == 'dev'
Requires-Dist: tox>=4.25.0; extra == 'dev'
Requires-Dist: types-python-dateutil>=2.9.0; extra == 'dev'
Requires-Dist: types-pyyaml>=6.0.0; extra == 'dev'
Requires-Dist: types-urllib3>=1.26.0; extra == 'dev'
Requires-Dist: yamllint>=1.37.0; extra == 'dev'
Provides-Extra: docs
Requires-Dist: mkdocs-gen-files>=0.5.0; extra == 'docs'
Requires-Dist: mkdocs-literate-nav>=0.6.0; extra == 'docs'
Requires-Dist: mkdocs-material>=9.7.0; extra == 'docs'
Requires-Dist: mkdocs-swagger-ui-tag>=0.7.1; extra == 'docs'
Requires-Dist: mkdocs>=1.6.0; extra == 'docs'
Requires-Dist: mkdocstrings[python]>=0.29.0; extra == 'docs'
